pylink/__init__.py
pylink/__main__.py
pylink/binpacker.py
pylink/decorators.py
pylink/enums.py
pylink/errors.py
pylink/jlink.py
pylink/jlock.py
pylink/library.py
pylink/registers.py
pylink/structs.py
pylink/threads.py
pylink/util.py
pylink/protocols/__init__.py
pylink/protocols/swd.py
pylink/unlockers/__init__.py
pylink/unlockers/unlock_kinetis.py
pylink_square-2.0.0.data/scripts/pylink-rtt
pylink_square-2.0.0.data/scripts/pylink-swv
pylink_square-2.0.0.dist-info/licenses/LICENSE.md
pylink_square-2.0.0.dist-info/METADATA
pylink_square-2.0.0.dist-info/WHEEL
pylink_square-2.0.0.dist-info/entry_points.txt
pylink_square-2.0.0.dist-info/top_level.txt
pylink_square-2.0.0.dist-info/RECORD
