Metadata-Version: 2.4
Name: pylink-square
Version: 2.0.0
Summary: Python interface for SEGGER J-Link.
Home-page: http://www.github.com/Square/pylink
Author: Square Embedded Software Team
Author-email: esw-team@squareup.com
License: Apache 2.0
Keywords: SEGGER J-Link
Requires-Python: >=3.0
License-File: LICENSE.md
Requires-Dist: psutil>=5.2.2
Requires-Dist: six
Provides-Extra: dev
Requires-Dist: behave==1.2.5; extra == "dev"
Requires-Dist: coverage==4.4.1; extra == "dev"
Requires-Dist: psutil>=5.2.2; extra == "dev"
Requires-Dist: pycodestyle>=2.3.1; extra == "dev"
Requires-Dist: setuptools>=70.2.0; extra == "dev"
Requires-Dist: six; extra == "dev"
Requires-Dist: sphinx==1.4.8; extra == "dev"
Requires-Dist: sphinx-argparse==0.1.15; extra == "dev"
Requires-Dist: sphinx_rtd_theme==0.2.4; extra == "dev"
Requires-Dist: sphinxcontrib-napoleon==0.5.3; extra == "dev"
Requires-Dist: wheel; extra == "dev"
Provides-Extra: test
Requires-Dist: mock==2.0.0; extra == "test"
Dynamic: author
Dynamic: author-email
Dynamic: description
Dynamic: home-page
Dynamic: keywords
Dynamic: license
Dynamic: license-file
Dynamic: requires-dist
Dynamic: requires-python
Dynamic: summary
